GeminiAIChat/.env
GeminiAIChat/__init__.py
GeminiAIChat/core.py
GeminiAIChat/process.py
geminiai_chat_python-0.4.dist-info/METADATA
geminiai_chat_python-0.4.dist-info/WHEEL
geminiai_chat_python-0.4.dist-info/top_level.txt
geminiai_chat_python-0.4.dist-info/RECORD
