Metadata-Version: 2.1
Name: geminiai-chat-python
Version: 0.4
Summary: GeminiAI-Chat enables easy integration of AI Chat functionalities into Python projects.
Home-page: UNKNOWN
Author: mominiqbal1234
Author-email: <mominiqbal1214@gmail.com>
License: UNKNOWN
Keywords: geminiai-chat-python,python,geminiai-chat,geminiai
Platform: UNKNOWN
Classifier: Development Status :: 1 - Planning
Classifier: Intended Audience :: Developers
Classifier: Programming Language :: Python :: 3
Classifier: Operating System :: Unix
Classifier: Operating System :: MacOS :: MacOS X
Classifier: Operating System :: Microsoft :: Windows
Requires-Dist: google-api-python-client
Requires-Dist: google-generativeai
Requires-Dist: httpx
